html_email_sender/__init__.py
html_email_sender/sender.py
html_email_sender-0.1.dist-info/METADATA
html_email_sender-0.1.dist-info/WHEEL
html_email_sender-0.1.dist-info/top_level.txt
html_email_sender-0.1.dist-info/RECORD
