Metadata-Version: 2.1
Name: html-email-sender
Version: 0.1
Requires-Dist: Jinja2
